SonoffBasic/__init__.py
SonoffBasic/sonoff.py
SonoffBasic-0.0.2.dist-info/LICENSE
SonoffBasic-0.0.2.dist-info/METADATA
SonoffBasic-0.0.2.dist-info/WHEEL
SonoffBasic-0.0.2.dist-info/top_level.txt
SonoffBasic-0.0.2.dist-info/RECORD
