Metadata-Version: 2.1
Name: SonoffBasic
Version: 0.0.2
Summary: basic package to control sonoff switches
Home-page: https://github.com/devnicolasc/SonoffBasic
Author: Nicolas Golovaty
Author-email: nicolascho2@gmail.com
License: UNKNOWN
Platform: UNKNOWN
Classifier: Programming Language :: Python :: 3
Classifier: License :: OSI Approved :: MIT License
Classifier: Operating System :: OS Independent
Requires-Python: >=3.6
Requires-Dist: aiohttp (==3.7.3)
Requires-Dist: requests (==2.25.1)
